firewheel_repo_layer2/ovs/.gitignore
firewheel_repo_layer2/ovs/MANIFEST
firewheel_repo_layer2/ovs/README.rst
firewheel_repo_layer2/ovs/model_component_objects.py
firewheel_repo_layer2/ovs/INSTALL/tasks.yml
firewheel_repo_layer2/ovs/INSTALL/vars.yml
firewheel_repo_layer2/ovs/vm_resources/bridge_layer2.sh
firewheel_repo_layer2/tap/MANIFEST
firewheel_repo_layer2/tap/README.rst
firewheel_repo_layer2/tap/model_component_objects.py
firewheel_repo_layer2/tap/plugin.py
firewheel_repo_layer2-3.0.0.dist-info/licenses/LICENSE
firewheel_repo_layer2-3.0.0.dist-info/METADATA
firewheel_repo_layer2-3.0.0.dist-info/WHEEL
firewheel_repo_layer2-3.0.0.dist-info/entry_points.txt
firewheel_repo_layer2-3.0.0.dist-info/top_level.txt
firewheel_repo_layer2-3.0.0.dist-info/RECORD
